apps.py
fields.py
models.py
tests.py
veryfi.py
migrations/0001_initial.py
migrations/__init__.py
dj_veryfi-0.1.8.dist-info/LICENSE
dj_veryfi-0.1.8.dist-info/METADATA
dj_veryfi-0.1.8.dist-info/WHEEL
dj_veryfi-0.1.8.dist-info/top_level.txt
dj_veryfi-0.1.8.dist-info/RECORD
