Metadata-Version: 2.1
Name: dj-veryfi
Version: 0.1.8
Summary: Django integration for Veryfi OCR API.
Home-page: https://github.com/tonykamillo/dj-veryfi
Author: Tony Kamillo
Author-email: tonykamillo@gmail.com
License: DBAD
Classifier: Environment :: Web Environment
Classifier: Framework :: Django
Classifier: Intended Audience :: Developers
Classifier: License :: OSI Approved :: BSD License
Classifier: Operating System :: OS Independent
Classifier: Programming Language :: Python
Classifier: Programming Language :: Python :: 3
Requires-Python: >=3.8
License-File: LICENSE
Requires-Dist: Django (>=3.2.20)
Requires-Dist: veryfi (>=3.3.0)
Requires-Dist: model-bakery (>=1.12.0)
